losiquant/__init__.py
losiquant/Backend/__init__.py
losiquant/Backend/cpu.py
losiquant/Backend/micro.py
losiquant/core/__init__.py
losiquant/core/bitpack.py
losiquant/core/decoder.py
losiquant/core/engine.py
losiquant/formats/__init__.py
losiquant/formats/lsq_model.py
losiquant-1.0.0.1.dist-info/licenses/LICENSE
losiquant-1.0.0.1.dist-info/METADATA
losiquant-1.0.0.1.dist-info/WHEEL
losiquant-1.0.0.1.dist-info/top_level.txt
losiquant-1.0.0.1.dist-info/RECORD
