Metadata-Version: 2.4
Name: losiquant
Version: 1.0.0.1
Summary: LOSIQUANT: High-fidelity logarithmic quantization for neural networks
Author-email: Loukmane Hadj Said <loukmanehadjsaid56@gmail.com>
License: Apache-2.0
Project-URL: Homepage, https://github.com/MyOptimalNext/losiquant 
Project-URL: Repository, https://github.com/MyOptimalNext/losiquant 
Project-URL: Issues, https://github.com/MyOptimalNext/losiquant/issues 
Keywords: quantization,neural-networks,edge-ai,tinyml,compression,logarithmic
Classifier: Development Status :: 3 - Alpha
Classifier: Intended Audience :: Developers
Classifier: Intended Audience :: Science/Research
Classifier: License :: OSI Approved :: Apache Software License
Classifier: Operating System :: OS Independent
Classifier: Programming Language :: Python :: 3
Classifier: Programming Language :: Python :: 3.8
Classifier: Programming Language :: Python :: 3.9
Classifier: Programming Language :: Python :: 3.10
Classifier: Programming Language :: Python :: 3.11
Classifier: Topic :: Scientific/Engineering :: Artificial Intelligence
Classifier: Topic :: Software Development :: Libraries :: Python Modules
Requires-Python: >=3.8
License-File: LICENSE
Requires-Dist: torch>=1.13.0
Requires-Dist: numpy>=1.21.0
Provides-Extra: dev
Requires-Dist: pytest; extra == "dev"
Requires-Dist: mkdocs; extra == "dev"
Dynamic: license-file
